search_kwic/__init__.py
search_kwic/model.py
search_kwic/search.py
search_kwic-0.2.dist-info/METADATA
search_kwic-0.2.dist-info/RECORD
search_kwic-0.2.dist-info/WHEEL
search_kwic-0.2.dist-info/top_level.txt
