Metadata-Version: 2.1
Name: search-kwic
Version: 0.2
Summary: Tool for KWIC representation of paralleltext. Find a word in the parallel text corresponding to query in the original text.
Home-page: https://github.com/maria-terekhina/search_kwic
Author: Maria Terekhina
Author-email: maria.myslina@gmail.com
License: UNKNOWN
Download-URL: https://github.com/maria-terekhina/search_kwic/archive/0.1.tar.gz
Keywords: kwic,parallel,corpora,alignment
Platform: UNKNOWN
Requires-Dist: ufal.udpipe
